MANIFEST.in
README.rst
setup.py
motifopt.egg-info/PKG-INFO
motifopt.egg-info/SOURCES.txt
motifopt.egg-info/dependency_links.txt
motifopt.egg-info/top_level.txt
motifopt/input_data/baseline_config.txt
motifopt/input_data/data_cities/cities.txt
motifopt/input_data/data_cities/city_pairs.txt
motifopt/input_data/data_cities/city_pairs_rand_5K.txt
motifopt/output_data/motif_compare.png
motifopt/output_data/plot_motif_compare.plt
motifopt/output_data/single_motif/level_0_best_motif.txt
motifopt/output_data/single_motif/level_0_motif_metrics.txt
motifopt/output_data_generated/plot_motif_compare.plt
motifopt/scripts/01_get_time_varying_sat_positions.sh
motifopt/scripts/02_get_sat_positions_at_time.sh
motifopt/scripts/03_generate_single_motifs.sh
motifopt/scripts/04_generate_multi_motifs.sh
motifopt/scripts/calc_latencies.py
motifopt/scripts/find_multi_motifs.py
motifopt/scripts/find_single_motif.py
motifopt/scripts/get_sat_location.py
motifopt/scripts/make_valid_isls.py
motifopt/scripts/util.py
motifopt/scripts/vCITIES.txt
motifopt/scripts/vISLS.txt
motifopt/scripts/__pycache__/util.cpython-310.pyc