Metadata-Version: 2.1
Name: motifopt
Version: 1.2.0
Summary: Satellite Motif Optimization
Home-page: https://satnetwork.github.io
Author: Debopam Bhattacherjee
Author-email: your@address.com
License: MIT
Keywords: satellite motif optimization
Classifier: Development Status :: 3 - Alpha
Classifier: Intended Audience :: Developers
Classifier: Topic :: Software Development :: Build Tools
Classifier: License :: OSI Approved :: MIT License
Classifier: Programming Language :: Python :: 3.6
